snowflake_sql_api_async/__init__.py
snowflake_sql_api_async/connection.py
snowflake_sql_api_async-0.0.4.dist-info/licenses/LICENSE
snowflake_sql_api_async-0.0.4.dist-info/METADATA
snowflake_sql_api_async-0.0.4.dist-info/WHEEL
snowflake_sql_api_async-0.0.4.dist-info/top_level.txt
snowflake_sql_api_async-0.0.4.dist-info/RECORD
