Metadata-Version: 2.4
Name: snowflake-sql-api-async
Version: 0.0.4
Summary: Async library for querying Snowflake using SQL API.
Author-email: Jasper Chan <jasper@neonblue.ai>
License-Expression: MIT
Project-URL: Homepage, https://github.com/neonblue-ai/snowflake-sql-api-async
Project-URL: Issues, https://github.com/neonblue-ai/snowflake-sql-api-async/issues
Project-URL: Repository, https://github.com/neonblue-ai/snowflake-sql-api-async.git
Classifier: Programming Language :: Python :: 3
Classifier: Operating System :: OS Independent
Requires-Python: >=3.8
License-File: LICENSE
Requires-Dist: aiohttp>=3.8.0
Requires-Dist: PyJWT[crypto]>=2.6.0
Requires-Dist: snowflake-connector-python>=3.0.0
Requires-Dist: cryptography>=3.4.0
Provides-Extra: dev
Requires-Dist: pytest>=7.0.0; extra == "dev"
Requires-Dist: pytest-asyncio>=0.21.0; extra == "dev"
Requires-Dist: black>=22.0.0; extra == "dev"
Requires-Dist: isort>=5.10.0; extra == "dev"
Requires-Dist: mypy>=1.0.0; extra == "dev"
Requires-Dist: flake8>=5.0.0; extra == "dev"
Requires-Dist: build>=0.10.0; extra == "dev"
Requires-Dist: twine>=4.0.0; extra == "dev"
Requires-Dist: tomli>=2.0.0; python_version < "3.11" and extra == "dev"
Dynamic: license-file
